genai_tools-0.2.0.dist-info/METADATA
genai_tools-0.2.0.dist-info/WHEEL
genai_tools/LLMTask.py
genai_tools/__init__.py
genai_tools/openai_config.py
genai_tools/parser_classes.py
genai_tools/prompt_managerV2.py
genai_tools-0.2.0.dist-info/RECORD
